cmake_checker/__init__.py
cmake_checker/__main__.py
cmake_checker/components/__init__.py
cmake_checker/components/file_finder.py
cmake_checker/components/lexer.py
cmake_checker/components/parse_arguments.py
cmake_checker/components/reporter.py
cmake_checker/components/verifier.py
cmake_checker-0.1.3.dist-info/LICENSE
cmake_checker-0.1.3.dist-info/METADATA
cmake_checker-0.1.3.dist-info/WHEEL
cmake_checker-0.1.3.dist-info/top_level.txt
cmake_checker-0.1.3.dist-info/RECORD
