Metadata-Version: 2.1
Name: cmake-checker
Version: 0.1.3
Summary: cmake-checker is a tool to search for violations to 'modern' cmake rules.
Home-page: https://github.com/MaciejPatro/cmake-checker
Author: Maciej Patro
Author-email: maciejpatro@gmail.com
License: LICENSE
Platform: UNKNOWN
Classifier: License :: OSI Approved :: MIT License
Classifier: Programming Language :: Python
Classifier: Programming Language :: Python :: 3.5
Classifier: Programming Language :: Python :: Implementation :: CPython
Classifier: Programming Language :: Python :: Implementation :: PyPy
Requires-Python: >=3.5.0
Requires-Dist: ply (==3.11)
Requires-Dist: junit-xml (==1.8)
Requires-Dist: pathspec (==0.5.9)
